pgzip/__init__.py
pgzip/__main__.py
pgzip/pgzip.py
pgzip-0.4.0.dist-info/METADATA
pgzip-0.4.0.dist-info/WHEEL
pgzip-0.4.0.dist-info/licenses/LICENSE
pgzip-0.4.0.dist-info/RECORD
