Metadata-Version: 2.4
Name: pgzip
Version: 0.4.0
Summary: A multi-threading implementation of Python gzip module
Project-URL: Homepage, https://github.com/pgzip/pgzip
Author-email: Vincent Li <vincentliyx@gmail.com>, Tim Hughes <thughes@thegoldfish.org>
Maintainer-email: Tim Hughes <thughes@thegoldfish.org>
License: MIT License
License-File: LICENSE
Classifier: Development Status :: 4 - Beta
Classifier: Intended Audience :: Developers
Classifier: License :: OSI Approved :: MIT License
Classifier: Operating System :: OS Independent
Classifier: Programming Language :: Python :: 3
Classifier: Programming Language :: Python :: Implementation :: CPython
Classifier: Topic :: Software Development :: Libraries :: Python Modules
Requires-Python: >=3.10
